echovr_api/__init__.py
echovr_api/api.py
echovr_api/disk.py
echovr_api/game_state.py
echovr_api/last_score.py
echovr_api/player.py
echovr_api/stats.py
echovr_api/team.py
echovr_api/geometry/__init__.py
echovr_api/geometry/vector3d.py
echovr_api-0.2.0.dist-info/LICENSE
echovr_api-0.2.0.dist-info/METADATA
echovr_api-0.2.0.dist-info/WHEEL
echovr_api-0.2.0.dist-info/top_level.txt
echovr_api-0.2.0.dist-info/RECORD
