Metadata-Version: 2.1
Name: echovr-api
Version: 0.2.0
Summary: Python bindings for Echo VR's HTTP API.
Home-page: https://github.com/Ajedi32/echovr-api/
Author: Ajedi32
Author-email: ajedi32.web@gmail.com
License: UNKNOWN
Platform: UNKNOWN
Classifier: Programming Language :: Python :: 3
Classifier: License :: OSI Approved :: MIT License
Classifier: Operating System :: OS Independent
Classifier: Development Status :: 3 - Alpha
Classifier: Environment :: Console
Classifier: Intended Audience :: Developers
Classifier: Topic :: Games/Entertainment
Requires-Dist: requests
Provides-Extra: docs
Requires-Dist: sphinx (<2.0.0a0,>=1.8.2); extra == 'docs'
Requires-Dist: sphinx-autodoc-typehints (<2.0.0a0,>=1.5.0); extra == 'docs'
Requires-Dist: sphinxcontrib-apidoc (<0.4.0a0,>=0.3.0); extra == 'docs'
Requires-Dist: m2r (<0.3.0a0,>=0.2.1); extra == 'docs'
Requires-Dist: sphinx-rtd-theme (<0.5.0a0,>=0.4.2); extra == 'docs'
